{
    "plot": "shortwave_heating_rate_error.pdf",
    "name": "heating_rate_solar_error",
    "xlab": "Shortwave heating rate error (K/day)",
    "xlim": [-1, 1],
    "start_time": "2009-06-29",
    "base": [
        "../results/intermittency-fmr-base.nc",
        "../results/intermittency-base.nc"
    ],
    "products": [
        "../results/intermittency-fmr-1h.nc",
        "../results/intermittency-1h.nc"
    ],
    "col": ["#0169c9", "#0169c9"],
    "lty": [2, 1],
    "bg": ["#78c9ffff", "#0197fdff"]
}
